{"frames": [

{
	"filename": "Symbol 45 instance 10000",
	"frame": {"x":0,"y":0,"w":277,"h":15},
	"rotated": false,
	"trimmed": false,
	"spriteSourceSize": {"x":0,"y":0,"w":277,"h":15},
	"sourceSize": {"w":277,"h":15}
}
,{
	"filename": "Symbol 45 instance 10001",
	"frame": {"x":0,"y":15,"w":277,"h":15},
	"rotated": false,
	"trimmed": false,
	"spriteSourceSize": {"x":0,"y":0,"w":277,"h":15},
	"sourceSize": {"w":277,"h":15}
}],
"meta": {
	"app": "Adobe Animate",
	"version": "18.0.0.107",
	"image": "31.png",
	"format": "RGBA8888",
	"size": {"w":512,"h":512},
	"scale": "1"
}
}
